[
      {
        "type": "sourcecred/initiativeFile",
        "version": "0.2.0"
      },
      {
        "title": "Liquidity Rewards Week of 6/1/2021, 7:28:55 PM to 6/9/2021, 5:27:40 AM ",
        "timestampIso": "2021-06-09T12:27:40.000Z",
        "weight": {
          "incomplete": 0,
          "complete": 0
        },
        "completed": true,
        "champions": [],
        "dependencies": {},
        "references": {},
        "contributions":{ 
          "entries": [
        {
          "title": "Liquidity Provider: @Victor---Shenanigan",
          "timestampIso": "2021-06-09T12:27:40.000Z",
          "weight": 1.57321566727355971889,
          "contributors": ["Victor---Shenanigan"]
        },
        {
          "title": "Liquidity Provider: @Yalor--EST-",
          "timestampIso": "2021-06-09T12:27:40.000Z",
          "weight": 5.7380248712774133809,
          "contributors": ["Yalor--EST-"]
        },
        {
          "title": "Liquidity Provider: @FunctionalBen",
          "timestampIso": "2021-06-09T12:27:40.000Z",
          "weight": 0.03241525574714487463,
          "contributors": ["FunctionalBen"]
        },
        {
          "title": "Liquidity Provider: @Fluchtzwerg",
          "timestampIso": "2021-06-09T12:27:40.000Z",
          "weight": 0.01748340016747983243,
          "contributors": ["Fluchtzwerg"]
        },
        {
          "title": "Liquidity Provider: @shani",
          "timestampIso": "2021-06-09T12:27:40.000Z",
          "weight": 0.00088837839650196299,
          "contributors": ["shani"]
        },
        {
          "title": "Liquidity Provider: @tbull666",
          "timestampIso": "2021-06-09T12:27:40.000Z",
          "weight": 0.00866306924845079549,
          "contributors": ["tbull666"]
        },
        {
          "title": "Liquidity Provider: @reelitin",
          "timestampIso": "2021-06-09T12:27:40.000Z",
          "weight": 0.30543261515775002241,
          "contributors": ["reelitin"]
        },
        {
          "title": "Liquidity Provider: @abdullah",
          "timestampIso": "2021-06-09T12:27:40.000Z",
          "weight": 0.00038826565380774418,
          "contributors": ["abdullah"]
        },
        {
          "title": "Liquidity Provider: @pzoisme",
          "timestampIso": "2021-06-09T12:27:40.000Z",
          "weight": 0.02915643678084682805,
          "contributors": ["pzoisme"]
        },
        {
          "title": "Liquidity Provider: @ahmad097",
          "timestampIso": "2021-06-09T12:27:40.000Z",
          "weight": 0.00038671216117823627,
          "contributors": ["ahmad097"]
        },
        {
          "title": "Liquidity Provider: @borisblock",
          "timestampIso": "2021-06-09T12:27:40.000Z",
          "weight": 0.01065992676476754637,
          "contributors": ["borisblock"]
        },
        {
          "title": "Liquidity Provider: @probspot",
          "timestampIso": "2021-06-09T12:27:40.000Z",
          "weight": 0.00303903048115932499,
          "contributors": ["probspot"]
        },
        {
          "title": "Liquidity Provider: @xyo",
          "timestampIso": "2021-06-09T12:27:40.000Z",
          "weight": 0.03102768606207391849,
          "contributors": ["xyo"]
        },
        {
          "title": "Liquidity Provider: @Farrar1983",
          "timestampIso": "2021-06-09T12:27:40.000Z",
          "weight": 0.01230851545014390091,
          "contributors": ["Farrar1983"]
        },
        {
          "title": "Liquidity Provider: @Merlo",
          "timestampIso": "2021-06-09T12:27:40.000Z",
          "weight": 0.13052421920482494303,
          "contributors": ["Merlo"]
        },
        {
          "title": "Liquidity Provider: @Shaz",
          "timestampIso": "2021-06-09T12:27:40.000Z",
          "weight": 0.17662259310069924953,
          "contributors": ["Shaz"]
        },
        {
          "title": "Liquidity Provider: @anh",
          "timestampIso": "2021-06-09T12:27:40.000Z",
          "weight": 0.00099433719305449776,
          "contributors": ["anh"]
        },
        {
          "title": "Liquidity Provider: @F-THV",
          "timestampIso": "2021-06-09T12:27:40.000Z",
          "weight": 0.00424950490956973436,
          "contributors": ["F-THV"]
        },
        {
          "title": "Liquidity Provider: @Hoang-Trung",
          "timestampIso": "2021-06-09T12:27:40.000Z",
          "weight": 0.00074481548829314874,
          "contributors": ["Hoang-Trung"]
        },
        {
          "title": "Liquidity Provider: @sommi",
          "timestampIso": "2021-06-09T12:27:40.000Z",
          "weight": 0.66671001693421253284,
          "contributors": ["sommi"]
        },
        {
          "title": "Liquidity Provider: @Daniel-Derzic",
          "timestampIso": "2021-06-09T12:27:40.000Z",
          "weight": 0.02835978710835854844,
          "contributors": ["Daniel-Derzic"]
        },
        {
          "title": "Liquidity Provider: @khoapham91",
          "timestampIso": "2021-06-09T12:27:40.000Z",
          "weight": 0.00025705118332222797,
          "contributors": ["khoapham91"]
        },
        {
          "title": "Liquidity Provider: @tuanairdrop",
          "timestampIso": "2021-06-09T12:27:40.000Z",
          "weight": 0.00111599968044797167,
          "contributors": ["tuanairdrop"]
        },
        {
          "title": "Liquidity Provider: @dydymoon",
          "timestampIso": "2021-06-09T12:27:40.000Z",
          "weight": 0.00007176853187249785,
          "contributors": ["dydymoon"]
        },
        {
          "title": "Liquidity Provider: @juanospy94",
          "timestampIso": "2021-06-09T12:27:40.000Z",
          "weight": 0.01230599986330286676,
          "contributors": ["juanospy94"]
        },
        {
          "title": "Liquidity Provider: @cheo0202",
          "timestampIso": "2021-06-09T12:27:40.000Z",
          "weight": 0.04143118828081832222,
          "contributors": ["cheo0202"]
        },
        {
          "title": "Liquidity Provider: @mAcKz88",
          "timestampIso": "2021-06-09T12:27:40.000Z",
          "weight": 0.07502566411400451378,
          "contributors": ["mAcKz88"]
        },
        {
          "title": "Liquidity Provider: @diegoleal88",
          "timestampIso": "2021-06-09T12:27:40.000Z",
          "weight": 0.05768093641441593826,
          "contributors": ["diegoleal88"]
        },
        {
          "title": "Liquidity Provider: @unstatesloth",
          "timestampIso": "2021-06-09T12:27:40.000Z",
          "weight": 0.00679528278779548159,
          "contributors": ["unstatesloth"]
        },
        {
          "title": "Liquidity Provider: @Pepo",
          "timestampIso": "2021-06-09T12:27:40.000Z",
          "weight": 0.0418079558785169242,
          "contributors": ["Pepo"]
        },
        {
          "title": "Liquidity Provider: @Willydmq",
          "timestampIso": "2021-06-09T12:27:40.000Z",
          "weight": 0.00302983582988496202,
          "contributors": ["Willydmq"]
        },
        {
          "title": "Liquidity Provider: @sanchote",
          "timestampIso": "2021-06-09T12:27:40.000Z",
          "weight": 0.09786974777303889516,
          "contributors": ["sanchote"]
        },
        {
          "title": "Liquidity Provider: @llealg2",
          "timestampIso": "2021-06-09T12:27:40.000Z",
          "weight": 0.02215151788109706433,
          "contributors": ["llealg2"]
        },
        {
          "title": "Liquidity Provider: @My-name-is-Sylar---",
          "timestampIso": "2021-06-09T12:27:40.000Z",
          "weight": 0.00117437510499700157,
          "contributors": ["My-name-is-Sylar---"]
        },
        {
          "title": "Liquidity Provider: @Lewiii",
          "timestampIso": "2021-06-09T12:27:40.000Z",
          "weight": 0.00144421407199666753,
          "contributors": ["Lewiii"]
        },
        {
          "title": "Liquidity Provider: @Juan-david",
          "timestampIso": "2021-06-09T12:27:40.000Z",
          "weight": 0.00070629591081017605,
          "contributors": ["Juan-david"]
        },
        {
          "title": "Liquidity Provider: @joche",
          "timestampIso": "2021-06-09T12:27:40.000Z",
          "weight": 0.01267579306579394952,
          "contributors": ["joche"]
        },
        {
          "title": "Liquidity Provider: @JuanBerbesi",
          "timestampIso": "2021-06-09T12:27:40.000Z",
          "weight": 0.00646736377670785818,
          "contributors": ["JuanBerbesi"]
        },
        {
          "title": "Liquidity Provider: @jesiigh",
          "timestampIso": "2021-06-09T12:27:40.000Z",
          "weight": 0.00348215857909770136,
          "contributors": ["jesiigh"]
        },
        {
          "title": "Liquidity Provider: @Angeles",
          "timestampIso": "2021-06-09T12:27:40.000Z",
          "weight": 0.00052166178111184761,
          "contributors": ["Angeles"]
        },
        {
          "title": "Liquidity Provider: @Ismary-Mujica",
          "timestampIso": "2021-06-09T12:27:40.000Z",
          "weight": 0.01487278685436032307,
          "contributors": ["Ismary-Mujica"]
        },
        {
          "title": "Liquidity Provider: @sappu7",
          "timestampIso": "2021-06-09T12:27:40.000Z",
          "weight": 0.00081027306566399687,
          "contributors": ["sappu7"]
        },
        {
          "title": "Liquidity Provider: @joelmonges",
          "timestampIso": "2021-06-09T12:27:40.000Z",
          "weight": 0.00049890399412859018,
          "contributors": ["joelmonges"]
        },
        {
          "title": "Liquidity Provider: @shax",
          "timestampIso": "2021-06-09T12:27:40.000Z",
          "weight": 0.21777971393634307618,
          "contributors": ["shax"]
        },
        {
          "title": "Liquidity Provider: @ishoboy",
          "timestampIso": "2021-06-09T12:27:40.000Z",
          "weight": 0.06173126411980381971,
          "contributors": ["ishoboy"]
        },
        {
          "title": "Liquidity Provider: @blackhawk",
          "timestampIso": "2021-06-09T12:27:40.000Z",
          "weight": 0.0006058676820586923,
          "contributors": ["blackhawk"]
        },
        {
          "title": "Liquidity Provider: @santiago02",
          "timestampIso": "2021-06-09T12:27:40.000Z",
          "weight": 0.00031743847035405323,
          "contributors": ["santiago02"]
        },
        {
          "title": "Liquidity Provider: @fabio90",
          "timestampIso": "2021-06-09T12:27:40.000Z",
          "weight": 0.00238243082395703424,
          "contributors": ["fabio90"]
        },
        {
          "title": "Liquidity Provider: @MariaEstrada",
          "timestampIso": "2021-06-09T12:27:40.000Z",
          "weight": 0.00325023356911958081,
          "contributors": ["MariaEstrada"]
        },
        {
          "title": "Liquidity Provider: @FrankArmoton",
          "timestampIso": "2021-06-09T12:27:40.000Z",
          "weight": 0.08964114149624161502,
          "contributors": ["FrankArmoton"]
        },
        {
          "title": "Liquidity Provider: @romel",
          "timestampIso": "2021-06-09T12:27:40.000Z",
          "weight": 0.00189818699142459777,
          "contributors": ["romel"]
        },
        {
          "title": "Liquidity Provider: @Criptonaut",
          "timestampIso": "2021-06-09T12:27:40.000Z",
          "weight": 0.0015172014597300561,
          "contributors": ["Criptonaut"]
        },
        {
          "title": "Liquidity Provider: @Genesis",
          "timestampIso": "2021-06-09T12:27:40.000Z",
          "weight": 0.00078329727008613483,
          "contributors": ["Genesis"]
        },
        {
          "title": "Liquidity Provider: @carlos-garcia",
          "timestampIso": "2021-06-09T12:27:40.000Z",
          "weight": 0.00096474232515785384,
          "contributors": ["carlos-garcia"]
        },
        {
          "title": "Liquidity Provider: @Mayerling",
          "timestampIso": "2021-06-09T12:27:40.000Z",
          "weight": 0.01356441520732393641,
          "contributors": ["Mayerling"]
        },
        {
          "title": "Liquidity Provider: @Kilgore",
          "timestampIso": "2021-06-09T12:27:40.000Z",
          "weight": 0.86744439971675135208,
          "contributors": ["Kilgore"]
        },
        {
          "title": "Liquidity Provider: @Noe",
          "timestampIso": "2021-06-09T12:27:40.000Z",
          "weight": 0.05498254952365769802,
          "contributors": ["Noe"]
        },
        {
          "title": "Liquidity Provider: @charingane",
          "timestampIso": "2021-06-09T12:27:40.000Z",
          "weight": 0.00613951597019859358,
          "contributors": ["charingane"]
        },
        {
          "title": "Liquidity Provider: @Maiker-Mu-oz",
          "timestampIso": "2021-06-09T12:27:40.000Z",
          "weight": 0.01123189499421166164,
          "contributors": ["Maiker-Mu-oz"]
        },
        {
          "title": "Liquidity Provider: @Kitty",
          "timestampIso": "2021-06-09T12:27:40.000Z",
          "weight": 1.482513121186399055,
          "contributors": ["Kitty"]
        },
        {
          "title": "Liquidity Provider: @Yessire",
          "timestampIso": "2021-06-09T12:27:40.000Z",
          "weight": 0.02342931057593096711,
          "contributors": ["Yessire"]
        },
        {
          "title": "Liquidity Provider: @Arnaldo",
          "timestampIso": "2021-06-09T12:27:40.000Z",
          "weight": 0.00072598569018898208,
          "contributors": ["Arnaldo"]
        },
        {
          "title": "Liquidity Provider: @Yudimar",
          "timestampIso": "2021-06-09T12:27:40.000Z",
          "weight": 0.00969805931129575293,
          "contributors": ["Yudimar"]
        },
        {
          "title": "Liquidity Provider: @Gerson-Rodr-guez",
          "timestampIso": "2021-06-09T12:27:40.000Z",
          "weight": 0.00117086378360602781,
          "contributors": ["Gerson-Rodr-guez"]
        },
        {
          "title": "Liquidity Provider: @SurFlowCrypto-ypvqy-wam",
          "timestampIso": "2021-06-09T12:27:40.000Z",
          "weight": 0.03705588019857559472,
          "contributors": ["SurFlowCrypto-ypvqy-wam"]
        },
        {
          "title": "Liquidity Provider: @Erick-Hern-ndez",
          "timestampIso": "2021-06-09T12:27:40.000Z",
          "weight": 0.0043230379245229462,
          "contributors": ["Erick-Hern-ndez"]
        },
        {
          "title": "Liquidity Provider: @yelimar-labrador",
          "timestampIso": "2021-06-09T12:27:40.000Z",
          "weight": 0.00453351950204522226,
          "contributors": ["yelimar-labrador"]
        },
        {
          "title": "Liquidity Provider: @Mr-Pandax-discord",
          "timestampIso": "2021-06-09T12:27:40.000Z",
          "weight": 0.0009366910268848223,
          "contributors": ["Mr-Pandax-discord"]
        },
        {
          "title": "Liquidity Provider: @Yuviry",
          "timestampIso": "2021-06-09T12:27:40.000Z",
          "weight": 0.00460007064306532626,
          "contributors": ["Yuviry"]
        },
        {
          "title": "Liquidity Provider: @JuanSaez",
          "timestampIso": "2021-06-09T12:27:40.000Z",
          "weight": 0.01844131596473625784,
          "contributors": ["JuanSaez"]
        },
        {
          "title": "Liquidity Provider: @--Musashi13",
          "timestampIso": "2021-06-09T12:27:40.000Z",
          "weight": 0.00824010897087784757,
          "contributors": ["--Musashi13"]
        },
        {
          "title": "Liquidity Provider: @jasonschiprett-discord",
          "timestampIso": "2021-06-09T12:27:40.000Z",
          "weight": 0.89660586268097492336,
          "contributors": ["jasonschiprett-discord"]
        }]
      }
    }]